pipenv_check/__init__.py
pipenv_check/check.py
pipenv_check-0.0.7.dist-info/LICENSE
pipenv_check-0.0.7.dist-info/METADATA
pipenv_check-0.0.7.dist-info/WHEEL
pipenv_check-0.0.7.dist-info/entry_points.txt
pipenv_check-0.0.7.dist-info/top_level.txt
pipenv_check-0.0.7.dist-info/RECORD
